spaceone_dashboard_gen/__init__.py
spaceone_dashboard_gen/main.py
spaceone_dashboard_gen/templates/index.html
spaceone_dashboard_gen-0.1.8.dist-info/METADATA
spaceone_dashboard_gen-0.1.8.dist-info/WHEEL
spaceone_dashboard_gen-0.1.8.dist-info/entry_points.txt
spaceone_dashboard_gen-0.1.8.dist-info/top_level.txt
spaceone_dashboard_gen-0.1.8.dist-info/RECORD
