Metadata-Version: 2.2
Name: spaceone-dashboard-gen
Version: 0.1.8
Summary: A dashboard generator using FastAPI
Home-page: https://github.com/yourusername/spaceone-dashboard-gen
Author: seolmin
Author-email: seolmin@megazone.com
Classifier: Programming Language :: Python :: 3
Classifier: License :: OSI Approved :: MIT License
Classifier: Operating System :: OS Independent
Requires-Python: >=3.8
Requires-Dist: fastapi
Requires-Dist: uvicorn
Requires-Dist: pydantic>=2.0
Requires-Dist: pyyaml
Requires-Dist: jinja2
Dynamic: author
Dynamic: author-email
Dynamic: classifier
Dynamic: description
Dynamic: description-content-type
Dynamic: home-page
Dynamic: requires-dist
Dynamic: requires-python
Dynamic: summary
